{
  "masterId": 54,
  "operatingDays": [
    "Monday",
    "Tuesday",
    "Wednesday",
    "Thursday",
    "Friday",
    "Saturday",
    "Sunday"
  ],
  "offDays": [],
  "schedules": {},
  "trainData": {
    "train_code": "255",
    "begin": "Thon Buri",
    "end": "Lang Suan",
    "train_type": "Ordinary",
    "code": null,
    "line": "สายใต้",
    "bg_color": "#ffc233",
    "text_color": "#000000",
    "displayDate": null,
    "valid_from_th": "01-12-2567",
    "valid_until_th": null,
    "valid_from_en": "01-12-2024",
    "valid_until_en": null
  },
  "scheduleData": [
    {
      "row_num": "1",
      "stop_no": 1,
      "station_code": 4002,
      "station_name": "Thon Buri",
      "is_begin": 1,
      "is_end": 0,
      "arrive_time": null,
      "arriveplusdate": null,
      "arrive_date_th": null,
      "arrive_date_en": null,
      "depart_time": "07:20",
      "departplusdate": 0,
      "depart_date_th": "11-01-2569",
      "depart_date_en": null
    },
    {
      "row_num": "2",
      "stop_no": 2,
      "station_code": 4434,
      "station_name": "Jaran Sanitwong",
      "is_begin": 0,
      "is_end": 0,
      "arrive_time": "07:22",
      "arriveplusdate": 0,
      "arrive_date_th": "11-01-2569",
      "arrive_date_en": "11-01-2026",
      "depart_time": "07:23",
      "departplusdate": 0,
      "depart_date_th": "11-01-2569",
      "depart_date_en": "11-01-2026"
    },
    {
      "row_num": "3",
      "stop_no": 3,
      "station_code": 4003,
      "station_name": "Bang Ramat",
      "is_begin": 0,
      "is_end": 0,
      "arrive_time": "07:28",
      "arriveplusdate": 0,
      "arrive_date_th": "11-01-2569",
      "arrive_date_en": "11-01-2026",
      "depart_time": "07:29",
      "departplusdate": 0,
      "depart_date_th": "11-01-2569",
      "depart_date_en": "11-01-2026"
    },
    {
      "row_num": "4",
      "stop_no": 4,
      "station_code": 4004,
      "station_name": "Taling Chan Junction",
      "is_begin": 0,
      "is_end": 0,
      "arrive_time": "07:32",
      "arriveplusdate": 0,
      "arrive_date_th": "11-01-2569",
      "arrive_date_en": "11-01-2026",
      "depart_time": "07:33",
      "departplusdate": 0,
      "depart_date_th": "11-01-2569",
      "depart_date_en": "11-01-2026"
    },
    {
      "row_num": "5",
      "stop_no": 5,
      "station_code": 4007,
      "station_name": "Banchimphli",
      "is_begin": 0,
      "is_end": 0,
      "arrive_time": "07:36",
      "arriveplusdate": 0,
      "arrive_date_th": "11-01-2569",
      "arrive_date_en": "11-01-2026",
      "depart_time": "07:37",
      "departplusdate": 0,
      "depart_date_th": "11-01-2569",
      "depart_date_en": "11-01-2026"
    },
    {
      "row_num": "6",
      "stop_no": 7,
      "station_code": 4008,
      "station_name": "Sala Thammasop",
      "is_begin": 0,
      "is_end": 0,
      "arrive_time": "07:44",
      "arriveplusdate": 0,
      "arrive_date_th": "11-01-2569",
      "arrive_date_en": "11-01-2026",
      "depart_time": "07:45",
      "departplusdate": 0,
      "depart_date_th": "11-01-2569",
      "depart_date_en": "11-01-2026"
    },
    {
      "row_num": "7",
      "stop_no": 8,
      "station_code": 4009,
      "station_name": "Sala Ya",
      "is_begin": 0,
      "is_end": 0,
      "arrive_time": "07:50",
      "arriveplusdate": 0,
      "arrive_date_th": "11-01-2569",
      "arrive_date_en": "11-01-2026",
      "depart_time": "07:51",
      "departplusdate": 0,
      "depart_date_th": "11-01-2569",
      "depart_date_en": "11-01-2026"
    },
    {
      "row_num": "8",
      "stop_no": 9,
      "station_code": 4010,
      "station_name": "Wat Suwan",
      "is_begin": 0,
      "is_end": 0,
      "arrive_time": "07:57",
      "arriveplusdate": 0,
      "arrive_date_th": "11-01-2569",
      "arrive_date_en": "11-01-2026",
      "depart_time": "07:58",
      "departplusdate": 0,
      "depart_date_th": "11-01-2569",
      "depart_date_en": "11-01-2026"
    },
    {
      "row_num": "9",
      "stop_no": 10,
      "station_code": 4011,
      "station_name": "Khlong Maha Sawat",
      "is_begin": 0,
      "is_end": 0,
      "arrive_time": "08:03",
      "arriveplusdate": 0,
      "arrive_date_th": "11-01-2569",
      "arrive_date_en": "11-01-2026",
      "depart_time": "08:04",
      "departplusdate": 0,
      "depart_date_th": "11-01-2569",
      "depart_date_en": "11-01-2026"
    },
    {
      "row_num": "10",
      "stop_no": 11,
      "station_code": 4012,
      "station_name": "Wat Ngiu Rai",
      "is_begin": 0,
      "is_end": 0,
      "arrive_time": "08:09",
      "arriveplusdate": 0,
      "arrive_date_th": "11-01-2569",
      "arrive_date_en": "11-01-2026",
      "depart_time": "08:10",
      "departplusdate": 0,
      "depart_date_th": "11-01-2569",
      "depart_date_en": "11-01-2026"
    },
    {
      "row_num": "11",
      "stop_no": 12,
      "station_code": 4013,
      "station_name": "Nakhon Chaisi",
      "is_begin": 0,
      "is_end": 0,
      "arrive_time": "08:16",
      "arriveplusdate": 0,
      "arrive_date_th": "11-01-2569",
      "arrive_date_en": "11-01-2026",
      "depart_time": "08:17",
      "departplusdate": 0,
      "depart_date_th": "11-01-2569",
      "depart_date_en": "11-01-2026"
    },
    {
      "row_num": "12",
      "stop_no": 13,
      "station_code": 4014,
      "station_name": "Tha Chalaep",
      "is_begin": 0,
      "is_end": 0,
      "arrive_time": "08:23",
      "arriveplusdate": 0,
      "arrive_date_th": "11-01-2569",
      "arrive_date_en": "11-01-2026",
      "depart_time": "08:24",
      "departplusdate": 0,
      "depart_date_th": "11-01-2569",
      "depart_date_en": "11-01-2026"
    },
    {
      "row_num": "13",
      "stop_no": 14,
      "station_code": 4015,
      "station_name": "Ton Samrong",
      "is_begin": 0,
      "is_end": 0,
      "arrive_time": "08:30",
      "arriveplusdate": 0,
      "arrive_date_th": "11-01-2569",
      "arrive_date_en": "11-01-2026",
      "depart_time": "08:31",
      "departplusdate": 0,
      "depart_date_th": "11-01-2569",
      "depart_date_en": "11-01-2026"
    },
    {
      "row_num": "14",
      "stop_no": 15,
      "station_code": 4016,
      "station_name": "Nakhon Pathom",
      "is_begin": 0,
      "is_end": 0,
      "arrive_time": "08:35",
      "arriveplusdate": 0,
      "arrive_date_th": "11-01-2569",
      "arrive_date_en": "11-01-2026",
      "depart_time": "08:37",
      "departplusdate": 0,
      "depart_date_th": "11-01-2569",
      "depart_date_en": "11-01-2026"
    },
    {
      "row_num": "15",
      "stop_no": 16,
      "station_code": 4017,
      "station_name": "Sanam Chandra Palace",
      "is_begin": 0,
      "is_end": 0,
      "arrive_time": "08:40",
      "arriveplusdate": 0,
      "arrive_date_th": "11-01-2569",
      "arrive_date_en": "11-01-2026",
      "depart_time": "08:41",
      "departplusdate": 0,
      "depart_date_th": "11-01-2569",
      "depart_date_en": "11-01-2026"
    },
    {
      "row_num": "16",
      "stop_no": 17,
      "station_code": 4018,
      "station_name": "Phrong Madua",
      "is_begin": 0,
      "is_end": 0,
      "arrive_time": "08:46",
      "arriveplusdate": 0,
      "arrive_date_th": "11-01-2569",
      "arrive_date_en": "11-01-2026",
      "depart_time": "08:47",
      "departplusdate": 0,
      "depart_date_th": "11-01-2569",
      "depart_date_en": "11-01-2026"
    },
    {
      "row_num": "17",
      "stop_no": 18,
      "station_code": 4019,
      "station_name": "Khlong Bang Tan",
      "is_begin": 0,
      "is_end": 0,
      "arrive_time": "08:51",
      "arriveplusdate": 0,
      "arrive_date_th": "11-01-2569",
      "arrive_date_en": "11-01-2026",
      "depart_time": "08:52",
      "departplusdate": 0,
      "depart_date_th": "11-01-2569",
      "depart_date_en": "11-01-2026"
    },
    {
      "row_num": "18",
      "stop_no": 19,
      "station_code": 4020,
      "station_name": "Nong Pla Duk Junction",
      "is_begin": 0,
      "is_end": 0,
      "arrive_time": "08:58",
      "arriveplusdate": 0,
      "arrive_date_th": "11-01-2569",
      "arrive_date_en": "11-01-2026",
      "depart_time": "09:01",
      "departplusdate": 0,
      "depart_date_th": "11-01-2569",
      "depart_date_en": "11-01-2026"
    },
    {
      "row_num": "19",
      "stop_no": 20,
      "station_code": 4079,
      "station_name": "Ban Pong",
      "is_begin": 0,
      "is_end": 0,
      "arrive_time": "09:07",
      "arriveplusdate": 0,
      "arrive_date_th": "11-01-2569",
      "arrive_date_en": "11-01-2026",
      "depart_time": "09:08",
      "departplusdate": 0,
      "depart_date_th": "11-01-2569",
      "depart_date_en": "11-01-2026"
    },
    {
      "row_num": "20",
      "stop_no": 22,
      "station_code": 4082,
      "station_name": "Khlong Ta Khot",
      "is_begin": 0,
      "is_end": 0,
      "arrive_time": "09:21",
      "arriveplusdate": 0,
      "arrive_date_th": "11-01-2569",
      "arrive_date_en": "11-01-2026",
      "depart_time": "09:22",
      "departplusdate": 0,
      "depart_date_th": "11-01-2569",
      "depart_date_en": "11-01-2026"
    },
    {
      "row_num": "21",
      "stop_no": 23,
      "station_code": 4083,
      "station_name": "Photharam",
      "is_begin": 0,
      "is_end": 0,
      "arrive_time": "09:27",
      "arriveplusdate": 0,
      "arrive_date_th": "11-01-2569",
      "arrive_date_en": "11-01-2026",
      "depart_time": "09:28",
      "departplusdate": 0,
      "depart_date_th": "11-01-2569",
      "depart_date_en": "11-01-2026"
    },
    {
      "row_num": "22",
      "stop_no": 24,
      "station_code": 4085,
      "station_name": "Chet Samian",
      "is_begin": 0,
      "is_end": 0,
      "arrive_time": "09:35",
      "arriveplusdate": 0,
      "arrive_date_th": "11-01-2569",
      "arrive_date_en": "11-01-2026",
      "depart_time": "09:36",
      "departplusdate": 0,
      "depart_date_th": "11-01-2569",
      "depart_date_en": "11-01-2026"
    },
    {
      "row_num": "23",
      "stop_no": 27,
      "station_code": 4089,
      "station_name": "Ratchaburi",
      "is_begin": 0,
      "is_end": 0,
      "arrive_time": "09:49",
      "arriveplusdate": 0,
      "arrive_date_th": "11-01-2569",
      "arrive_date_en": "11-01-2026",
      "depart_time": "09:51",
      "departplusdate": 0,
      "depart_date_th": "11-01-2569",
      "depart_date_en": "11-01-2026"
    },
    {
      "row_num": "24",
      "stop_no": 31,
      "station_code": 4093,
      "station_name": "Pak Tho",
      "is_begin": 0,
      "is_end": 0,
      "arrive_time": "10:08",
      "arriveplusdate": 0,
      "arrive_date_th": "11-01-2569",
      "arrive_date_en": "11-01-2026",
      "depart_time": "10:09",
      "departplusdate": 0,
      "depart_date_th": "11-01-2569",
      "depart_date_en": "11-01-2026"
    },
    {
      "row_num": "25",
      "stop_no": 33,
      "station_code": 4095,
      "station_name": "Bang Khem",
      "is_begin": 0,
      "is_end": 0,
      "arrive_time": "10:17",
      "arriveplusdate": 0,
      "arrive_date_th": "11-01-2569",
      "arrive_date_en": "11-01-2026",
      "depart_time": "10:18",
      "departplusdate": 0,
      "depart_date_th": "11-01-2569",
      "depart_date_en": "11-01-2026"
    },
    {
      "row_num": "26",
      "stop_no": 37,
      "station_code": 4101,
      "station_name": "Phetchaburi",
      "is_begin": 0,
      "is_end": 0,
      "arrive_time": "10:39",
      "arriveplusdate": 0,
      "arrive_date_th": "11-01-2569",
      "arrive_date_en": "11-01-2026",
      "depart_time": "10:41",
      "departplusdate": 0,
      "depart_date_th": "11-01-2569",
      "depart_date_en": "11-01-2026"
    },
    {
      "row_num": "27",
      "stop_no": 38,
      "station_code": 4104,
      "station_name": "Khao Thamon",
      "is_begin": 0,
      "is_end": 0,
      "arrive_time": "10:50",
      "arriveplusdate": 0,
      "arrive_date_th": "11-01-2569",
      "arrive_date_en": "11-01-2026",
      "depart_time": "10:51",
      "departplusdate": 0,
      "depart_date_th": "11-01-2569",
      "depart_date_en": "11-01-2026"
    },
    {
      "row_num": "28",
      "stop_no": 39,
      "station_code": 4105,
      "station_name": "Nong Mai Luang",
      "is_begin": 0,
      "is_end": 0,
      "arrive_time": "10:55",
      "arriveplusdate": 0,
      "arrive_date_th": "11-01-2569",
      "arrive_date_en": "11-01-2026",
      "depart_time": "10:56",
      "departplusdate": 0,
      "depart_date_th": "11-01-2569",
      "depart_date_en": "11-01-2026"
    },
    {
      "row_num": "29",
      "stop_no": 40,
      "station_code": 4107,
      "station_name": "Nong Chok",
      "is_begin": 0,
      "is_end": 0,
      "arrive_time": "11:02",
      "arriveplusdate": 0,
      "arrive_date_th": "11-01-2569",
      "arrive_date_en": "11-01-2026",
      "depart_time": "11:03",
      "departplusdate": 0,
      "depart_date_th": "11-01-2569",
      "depart_date_en": "11-01-2026"
    },
    {
      "row_num": "30",
      "stop_no": 41,
      "station_code": 4108,
      "station_name": "Nong Sala",
      "is_begin": 0,
      "is_end": 0,
      "arrive_time": "11:09",
      "arriveplusdate": 0,
      "arrive_date_th": "11-01-2569",
      "arrive_date_en": "11-01-2026",
      "depart_time": "11:10",
      "departplusdate": 0,
      "depart_date_th": "11-01-2569",
      "depart_date_en": "11-01-2026"
    },
    {
      "row_num": "31",
      "stop_no": 42,
      "station_code": 4111,
      "station_name": "Cha-am",
      "is_begin": 0,
      "is_end": 0,
      "arrive_time": "11:20",
      "arriveplusdate": 0,
      "arrive_date_th": "11-01-2569",
      "arrive_date_en": "11-01-2026",
      "depart_time": "11:21",
      "departplusdate": 0,
      "depart_date_th": "11-01-2569",
      "depart_date_en": "11-01-2026"
    },
    {
      "row_num": "32",
      "stop_no": 43,
      "station_code": 4114,
      "station_name": "Huai Sai Nua",
      "is_begin": 0,
      "is_end": 0,
      "arrive_time": "11:30",
      "arriveplusdate": 0,
      "arrive_date_th": "11-01-2569",
      "arrive_date_en": "11-01-2026",
      "depart_time": "11:31",
      "departplusdate": 0,
      "depart_date_th": "11-01-2569",
      "depart_date_en": "11-01-2026"
    },
    {
      "row_num": "33",
      "stop_no": 44,
      "station_code": 4115,
      "station_name": "Huai Sai Tai",
      "is_begin": 0,
      "is_end": 0,
      "arrive_time": "11:35",
      "arriveplusdate": 0,
      "arrive_date_th": "11-01-2569",
      "arrive_date_en": "11-01-2026",
      "depart_time": "11:36",
      "departplusdate": 0,
      "depart_date_th": "11-01-2569",
      "depart_date_en": "11-01-2026"
    },
    {
      "row_num": "34",
      "stop_no": 45,
      "station_code": 4118,
      "station_name": "Hua Hin",
      "is_begin": 0,
      "is_end": 0,
      "arrive_time": "11:46",
      "arriveplusdate": 0,
      "arrive_date_th": "11-01-2569",
      "arrive_date_en": "11-01-2026",
      "depart_time": "11:49",
      "departplusdate": 0,
      "depart_date_th": "11-01-2569",
      "depart_date_en": "11-01-2026"
    },
    {
      "row_num": "35",
      "stop_no": 46,
      "station_code": 4119,
      "station_name": "Nong Kae",
      "is_begin": 0,
      "is_end": 0,
      "arrive_time": "11:54",
      "arriveplusdate": 0,
      "arrive_date_th": "11-01-2569",
      "arrive_date_en": "11-01-2026",
      "depart_time": "11:55",
      "departplusdate": 0,
      "depart_date_th": "11-01-2569",
      "depart_date_en": "11-01-2026"
    },
    {
      "row_num": "36",
      "stop_no": 47,
      "station_code": 4120,
      "station_name": "Suan Soan Pradipat",
      "is_begin": 0,
      "is_end": 0,
      "arrive_time": "12:00",
      "arriveplusdate": 0,
      "arrive_date_th": "11-01-2569",
      "arrive_date_en": "11-01-2026",
      "depart_time": "12:01",
      "departplusdate": 0,
      "depart_date_th": "11-01-2569",
      "depart_date_en": "11-01-2026"
    },
    {
      "row_num": "37",
      "stop_no": 49,
      "station_code": 4123,
      "station_name": "Wang Phong",
      "is_begin": 0,
      "is_end": 0,
      "arrive_time": "12:11",
      "arriveplusdate": 0,
      "arrive_date_th": "11-01-2569",
      "arrive_date_en": "11-01-2026",
      "depart_time": "12:12",
      "departplusdate": 0,
      "depart_date_th": "11-01-2569",
      "depart_date_en": "11-01-2026"
    },
    {
      "row_num": "38",
      "stop_no": 50,
      "station_code": 4124,
      "station_name": "Pran Buri",
      "is_begin": 0,
      "is_end": 0,
      "arrive_time": "12:16",
      "arriveplusdate": 0,
      "arrive_date_th": "11-01-2569",
      "arrive_date_en": "11-01-2026",
      "depart_time": "12:17",
      "departplusdate": 0,
      "depart_date_th": "11-01-2569",
      "depart_date_en": "11-01-2026"
    },
    {
      "row_num": "39",
      "stop_no": 51,
      "station_code": 4125,
      "station_name": "Huai Khwang",
      "is_begin": 0,
      "is_end": 0,
      "arrive_time": "12:23",
      "arriveplusdate": 0,
      "arrive_date_th": "11-01-2569",
      "arrive_date_en": "11-01-2026",
      "depart_time": "12:24",
      "departplusdate": 0,
      "depart_date_th": "11-01-2569",
      "depart_date_en": "11-01-2026"
    },
    {
      "row_num": "40",
      "stop_no": 52,
      "station_code": 4126,
      "station_name": "Nong Khang",
      "is_begin": 0,
      "is_end": 0,
      "arrive_time": "12:29",
      "arriveplusdate": 0,
      "arrive_date_th": "11-01-2569",
      "arrive_date_en": "11-01-2026",
      "depart_time": "12:30",
      "departplusdate": 0,
      "depart_date_th": "11-01-2569",
      "depart_date_en": "11-01-2026"
    },
    {
      "row_num": "41",
      "stop_no": 53,
      "station_code": 4128,
      "station_name": "Sam Roi Yot",
      "is_begin": 0,
      "is_end": 0,
      "arrive_time": "12:37",
      "arriveplusdate": 0,
      "arrive_date_th": "11-01-2569",
      "arrive_date_en": "11-01-2026",
      "depart_time": "12:38",
      "departplusdate": 0,
      "depart_date_th": "11-01-2569",
      "depart_date_en": "11-01-2026"
    },
    {
      "row_num": "42",
      "stop_no": 54,
      "station_code": 4130,
      "station_name": "Sam Krathai",
      "is_begin": 0,
      "is_end": 0,
      "arrive_time": "12:44",
      "arriveplusdate": 0,
      "arrive_date_th": "11-01-2569",
      "arrive_date_en": "11-01-2026",
      "depart_time": "12:45",
      "departplusdate": 0,
      "depart_date_th": "11-01-2569",
      "depart_date_en": "11-01-2026"
    },
    {
      "row_num": "43",
      "stop_no": 55,
      "station_code": 4133,
      "station_name": "Kui Buri",
      "is_begin": 0,
      "is_end": 0,
      "arrive_time": "12:54",
      "arriveplusdate": 0,
      "arrive_date_th": "11-01-2569",
      "arrive_date_en": "11-01-2026",
      "depart_time": "12:55",
      "departplusdate": 0,
      "depart_date_th": "11-01-2569",
      "depart_date_en": "11-01-2026"
    },
    {
      "row_num": "44",
      "stop_no": 56,
      "station_code": 4135,
      "station_name": "Bo Nok",
      "is_begin": 0,
      "is_end": 0,
      "arrive_time": "13:02",
      "arriveplusdate": 0,
      "arrive_date_th": "11-01-2569",
      "arrive_date_en": "11-01-2026",
      "depart_time": "13:03",
      "departplusdate": 0,
      "depart_date_th": "11-01-2569",
      "depart_date_en": "11-01-2026"
    },
    {
      "row_num": "45",
      "stop_no": 57,
      "station_code": 4138,
      "station_name": "Thung Mamao",
      "is_begin": 0,
      "is_end": 0,
      "arrive_time": "13:12",
      "arriveplusdate": 0,
      "arrive_date_th": "11-01-2569",
      "arrive_date_en": "11-01-2026",
      "depart_time": "13:13",
      "departplusdate": 0,
      "depart_date_th": "11-01-2569",
      "depart_date_en": "11-01-2026"
    },
    {
      "row_num": "46",
      "stop_no": 58,
      "station_code": 4140,
      "station_name": "Khan Kradai",
      "is_begin": 0,
      "is_end": 0,
      "arrive_time": "13:19",
      "arriveplusdate": 0,
      "arrive_date_th": "11-01-2569",
      "arrive_date_en": "11-01-2026",
      "depart_time": "13:20",
      "departplusdate": 0,
      "depart_date_th": "11-01-2569",
      "depart_date_en": "11-01-2026"
    },
    {
      "row_num": "47",
      "stop_no": 59,
      "station_code": 4142,
      "station_name": "Prachuap Khiri Khan",
      "is_begin": 0,
      "is_end": 0,
      "arrive_time": "13:27",
      "arriveplusdate": 0,
      "arrive_date_th": "11-01-2569",
      "arrive_date_en": "11-01-2026",
      "depart_time": "13:28",
      "departplusdate": 0,
      "depart_date_th": "11-01-2569",
      "depart_date_en": "11-01-2026"
    },
    {
      "row_num": "48",
      "stop_no": 60,
      "station_code": 4144,
      "station_name": "Nong Hin",
      "is_begin": 0,
      "is_end": 0,
      "arrive_time": "13:35",
      "arriveplusdate": 0,
      "arrive_date_th": "11-01-2569",
      "arrive_date_en": "11-01-2026",
      "depart_time": "13:36",
      "departplusdate": 0,
      "depart_date_th": "11-01-2569",
      "depart_date_en": "11-01-2026"
    },
    {
      "row_num": "49",
      "stop_no": 61,
      "station_code": 4145,
      "station_name": "Whagor",
      "is_begin": 0,
      "is_end": 0,
      "arrive_time": "13:40",
      "arriveplusdate": 0,
      "arrive_date_th": "11-01-2569",
      "arrive_date_en": "11-01-2026",
      "depart_time": "13:41",
      "departplusdate": 0,
      "depart_date_th": "11-01-2569",
      "depart_date_en": "11-01-2026"
    },
    {
      "row_num": "50",
      "stop_no": 62,
      "station_code": 4146,
      "station_name": "Wang Duan",
      "is_begin": 0,
      "is_end": 0,
      "arrive_time": "13:46",
      "arriveplusdate": 0,
      "arrive_date_th": "11-01-2569",
      "arrive_date_en": "11-01-2026",
      "depart_time": "13:47",
      "departplusdate": 0,
      "depart_date_th": "11-01-2569",
      "depart_date_en": "11-01-2026"
    },
    {
      "row_num": "51",
      "stop_no": 63,
      "station_code": 4149,
      "station_name": "Huai Yang",
      "is_begin": 0,
      "is_end": 0,
      "arrive_time": "13:56",
      "arriveplusdate": 0,
      "arrive_date_th": "11-01-2569",
      "arrive_date_en": "11-01-2026",
      "depart_time": "13:57",
      "departplusdate": 0,
      "depart_date_th": "11-01-2569",
      "depart_date_en": "11-01-2026"
    },
    {
      "row_num": "52",
      "stop_no": 64,
      "station_code": 4152,
      "station_name": "Thung Pradu",
      "is_begin": 0,
      "is_end": 0,
      "arrive_time": "14:06",
      "arriveplusdate": 0,
      "arrive_date_th": "11-01-2569",
      "arrive_date_en": "11-01-2026",
      "depart_time": "14:07",
      "departplusdate": 0,
      "depart_date_th": "11-01-2569",
      "depart_date_en": "11-01-2026"
    },
    {
      "row_num": "53",
      "stop_no": 65,
      "station_code": 4153,
      "station_name": "Thap Sakae",
      "is_begin": 0,
      "is_end": 0,
      "arrive_time": "14:11",
      "arriveplusdate": 0,
      "arrive_date_th": "11-01-2569",
      "arrive_date_en": "11-01-2026",
      "depart_time": "14:12",
      "departplusdate": 0,
      "depart_date_th": "11-01-2569",
      "depart_date_en": "11-01-2026"
    },
    {
      "row_num": "54",
      "stop_no": 66,
      "station_code": 4154,
      "station_name": "Don Sai",
      "is_begin": 0,
      "is_end": 0,
      "arrive_time": "14:17",
      "arriveplusdate": 0,
      "arrive_date_th": "11-01-2569",
      "arrive_date_en": "11-01-2026",
      "depart_time": "14:18",
      "departplusdate": 0,
      "depart_date_th": "11-01-2569",
      "depart_date_en": "11-01-2026"
    },
    {
      "row_num": "55",
      "stop_no": 67,
      "station_code": 4156,
      "station_name": "Khok Ta Hom",
      "is_begin": 0,
      "is_end": 0,
      "arrive_time": "14:24",
      "arriveplusdate": 0,
      "arrive_date_th": "11-01-2569",
      "arrive_date_en": "11-01-2026",
      "depart_time": "14:25",
      "departplusdate": 0,
      "depart_date_th": "11-01-2569",
      "depart_date_en": "11-01-2026"
    },
    {
      "row_num": "56",
      "stop_no": 68,
      "station_code": 4158,
      "station_name": "Ban Krut",
      "is_begin": 0,
      "is_end": 0,
      "arrive_time": "14:32",
      "arriveplusdate": 0,
      "arrive_date_th": "11-01-2569",
      "arrive_date_en": "11-01-2026",
      "depart_time": "14:33",
      "departplusdate": 0,
      "depart_date_th": "11-01-2569",
      "depart_date_en": "11-01-2026"
    },
    {
      "row_num": "57",
      "stop_no": 69,
      "station_code": 4159,
      "station_name": "Nong Mongkhon",
      "is_begin": 0,
      "is_end": 0,
      "arrive_time": "14:39",
      "arriveplusdate": 0,
      "arrive_date_th": "11-01-2569",
      "arrive_date_en": "11-01-2026",
      "depart_time": "14:40",
      "departplusdate": 0,
      "depart_date_th": "11-01-2569",
      "depart_date_en": "11-01-2026"
    },
    {
      "row_num": "58",
      "stop_no": 70,
      "station_code": 4161,
      "station_name": "Na Phak Khuang",
      "is_begin": 0,
      "is_end": 0,
      "arrive_time": "14:45",
      "arriveplusdate": 0,
      "arrive_date_th": "11-01-2569",
      "arrive_date_en": "11-01-2026",
      "depart_time": "14:46",
      "departplusdate": 0,
      "depart_date_th": "11-01-2569",
      "depart_date_en": "11-01-2026"
    },
    {
      "row_num": "59",
      "stop_no": 71,
      "station_code": 4163,
      "station_name": "Bang Saphan Yai",
      "is_begin": 0,
      "is_end": 0,
      "arrive_time": "14:52",
      "arriveplusdate": 0,
      "arrive_date_th": "11-01-2569",
      "arrive_date_en": "11-01-2026",
      "depart_time": "14:53",
      "departplusdate": 0,
      "depart_date_th": "11-01-2569",
      "depart_date_en": "11-01-2026"
    },
    {
      "row_num": "60",
      "stop_no": 72,
      "station_code": 4164,
      "station_name": "Hin Gong",
      "is_begin": 0,
      "is_end": 0,
      "arrive_time": "15:00",
      "arriveplusdate": 0,
      "arrive_date_th": "11-01-2569",
      "arrive_date_en": "11-01-2026",
      "depart_time": "15:01",
      "departplusdate": 0,
      "depart_date_th": "11-01-2569",
      "depart_date_en": "11-01-2026"
    },
    {
      "row_num": "61",
      "stop_no": 73,
      "station_code": 4165,
      "station_name": "Cha Muang",
      "is_begin": 0,
      "is_end": 0,
      "arrive_time": "15:04",
      "arriveplusdate": 0,
      "arrive_date_th": "11-01-2569",
      "arrive_date_en": "11-01-2026",
      "depart_time": "15:05",
      "departplusdate": 0,
      "depart_date_th": "11-01-2569",
      "depart_date_en": "11-01-2026"
    },
    {
      "row_num": "62",
      "stop_no": 74,
      "station_code": 4167,
      "station_name": "Bang Saphan Noi",
      "is_begin": 0,
      "is_end": 0,
      "arrive_time": "15:12",
      "arriveplusdate": 0,
      "arrive_date_th": "11-01-2569",
      "arrive_date_en": "11-01-2026",
      "depart_time": "15:13",
      "departplusdate": 0,
      "depart_date_th": "11-01-2569",
      "depart_date_en": "11-01-2026"
    },
    {
      "row_num": "63",
      "stop_no": 75,
      "station_code": 4169,
      "station_name": "Huai Sak",
      "is_begin": 0,
      "is_end": 0,
      "arrive_time": "15:20",
      "arriveplusdate": 0,
      "arrive_date_th": "11-01-2569",
      "arrive_date_en": "11-01-2026",
      "depart_time": "15:21",
      "departplusdate": 0,
      "depart_date_th": "11-01-2569",
      "depart_date_en": "11-01-2026"
    },
    {
      "row_num": "64",
      "stop_no": 76,
      "station_code": 4172,
      "station_name": "Khao Chaiyarat",
      "is_begin": 0,
      "is_end": 0,
      "arrive_time": "15:33",
      "arriveplusdate": 0,
      "arrive_date_th": "11-01-2569",
      "arrive_date_en": "11-01-2026",
      "depart_time": "15:34",
      "departplusdate": 0,
      "depart_date_th": "11-01-2569",
      "depart_date_en": "11-01-2026"
    },
    {
      "row_num": "65",
      "stop_no": 77,
      "station_code": 4175,
      "station_name": "Map Ammarit",
      "is_begin": 0,
      "is_end": 0,
      "arrive_time": "15:44",
      "arriveplusdate": 0,
      "arrive_date_th": "11-01-2569",
      "arrive_date_en": "11-01-2026",
      "depart_time": "15:45",
      "departplusdate": 0,
      "depart_date_th": "11-01-2569",
      "depart_date_en": "11-01-2026"
    },
    {
      "row_num": "66",
      "stop_no": 78,
      "station_code": 4177,
      "station_name": "Ban Sap Somboon",
      "is_begin": 0,
      "is_end": 0,
      "arrive_time": "15:52",
      "arriveplusdate": 0,
      "arrive_date_th": "11-01-2569",
      "arrive_date_en": "11-01-2026",
      "depart_time": "15:53",
      "departplusdate": 0,
      "depart_date_th": "11-01-2569",
      "depart_date_en": "11-01-2026"
    },
    {
      "row_num": "67",
      "stop_no": 79,
      "station_code": 4178,
      "station_name": "Khlong Wang Chang",
      "is_begin": 0,
      "is_end": 0,
      "arrive_time": "15:59",
      "arriveplusdate": 0,
      "arrive_date_th": "11-01-2569",
      "arrive_date_en": "11-01-2026",
      "depart_time": "16:00",
      "departplusdate": 0,
      "depart_date_th": "11-01-2569",
      "depart_date_en": "11-01-2026"
    },
    {
      "row_num": "68",
      "stop_no": 80,
      "station_code": 4179,
      "station_name": "Pathiu",
      "is_begin": 0,
      "is_end": 0,
      "arrive_time": "16:05",
      "arriveplusdate": 0,
      "arrive_date_th": "11-01-2569",
      "arrive_date_en": "11-01-2026",
      "depart_time": "16:06",
      "departplusdate": 0,
      "depart_date_th": "11-01-2569",
      "depart_date_en": "11-01-2026"
    },
    {
      "row_num": "69",
      "stop_no": 81,
      "station_code": 4181,
      "station_name": "Ban Khok Ma",
      "is_begin": 0,
      "is_end": 0,
      "arrive_time": "16:14",
      "arriveplusdate": 0,
      "arrive_date_th": "11-01-2569",
      "arrive_date_en": "11-01-2026",
      "depart_time": "16:15",
      "departplusdate": 0,
      "depart_date_th": "11-01-2569",
      "depart_date_en": "11-01-2026"
    },
    {
      "row_num": "70",
      "stop_no": 82,
      "station_code": 4182,
      "station_name": "Saphli",
      "is_begin": 0,
      "is_end": 0,
      "arrive_time": "16:21",
      "arriveplusdate": 0,
      "arrive_date_th": "11-01-2569",
      "arrive_date_en": "11-01-2026",
      "depart_time": "16:22",
      "departplusdate": 0,
      "depart_date_th": "11-01-2569",
      "depart_date_en": "11-01-2026"
    },
    {
      "row_num": "71",
      "stop_no": 83,
      "station_code": 4183,
      "station_name": "Nong Nian",
      "is_begin": 0,
      "is_end": 0,
      "arrive_time": "16:27",
      "arriveplusdate": 0,
      "arrive_date_th": "11-01-2569",
      "arrive_date_en": "11-01-2026",
      "depart_time": "16:28",
      "departplusdate": 0,
      "depart_date_th": "11-01-2569",
      "depart_date_en": "11-01-2026"
    },
    {
      "row_num": "72",
      "stop_no": 84,
      "station_code": 4184,
      "station_name": "Na Cha-ang",
      "is_begin": 0,
      "is_end": 0,
      "arrive_time": "16:33",
      "arriveplusdate": 0,
      "arrive_date_th": "11-01-2569",
      "arrive_date_en": "11-01-2026",
      "depart_time": "16:34",
      "departplusdate": 0,
      "depart_date_th": "11-01-2569",
      "depart_date_en": "11-01-2026"
    },
    {
      "row_num": "73",
      "stop_no": 85,
      "station_code": 4186,
      "station_name": "Chumphon",
      "is_begin": 0,
      "is_end": 0,
      "arrive_time": "16:40",
      "arriveplusdate": 0,
      "arrive_date_th": "11-01-2569",
      "arrive_date_en": "11-01-2026",
      "depart_time": "16:50",
      "departplusdate": 0,
      "depart_date_th": "11-01-2569",
      "depart_date_en": "11-01-2026"
    },
    {
      "row_num": "74",
      "stop_no": 86,
      "station_code": 4187,
      "station_name": "Saeng Daet",
      "is_begin": 0,
      "is_end": 0,
      "arrive_time": "16:55",
      "arriveplusdate": 0,
      "arrive_date_th": "11-01-2569",
      "arrive_date_en": "11-01-2026",
      "depart_time": "17:00",
      "departplusdate": 0,
      "depart_date_th": "11-01-2569",
      "depart_date_en": "11-01-2026"
    },
    {
      "row_num": "75",
      "stop_no": 87,
      "station_code": 4189,
      "station_name": "Thung Kha",
      "is_begin": 0,
      "is_end": 0,
      "arrive_time": "17:08",
      "arriveplusdate": 0,
      "arrive_date_th": "11-01-2569",
      "arrive_date_en": "11-01-2026",
      "depart_time": "17:09",
      "departplusdate": 0,
      "depart_date_th": "11-01-2569",
      "depart_date_en": "11-01-2026"
    },
    {
      "row_num": "76",
      "stop_no": 88,
      "station_code": 4191,
      "station_name": "Wisai",
      "is_begin": 0,
      "is_end": 0,
      "arrive_time": "17:17",
      "arriveplusdate": 0,
      "arrive_date_th": "11-01-2569",
      "arrive_date_en": "11-01-2026",
      "depart_time": "17:18",
      "departplusdate": 0,
      "depart_date_th": "11-01-2569",
      "depart_date_en": "11-01-2026"
    },
    {
      "row_num": "77",
      "stop_no": 89,
      "station_code": 4192,
      "station_name": "Ban Khron",
      "is_begin": 0,
      "is_end": 0,
      "arrive_time": "17:24",
      "arriveplusdate": 0,
      "arrive_date_th": "11-01-2569",
      "arrive_date_en": "11-01-2026",
      "depart_time": "17:25",
      "departplusdate": 0,
      "depart_date_th": "11-01-2569",
      "depart_date_en": "11-01-2026"
    },
    {
      "row_num": "78",
      "stop_no": 90,
      "station_code": 4194,
      "station_name": "Sawi",
      "is_begin": 0,
      "is_end": 0,
      "arrive_time": "17:31",
      "arriveplusdate": 0,
      "arrive_date_th": "11-01-2569",
      "arrive_date_en": "11-01-2026",
      "depart_time": "17:32",
      "departplusdate": 0,
      "depart_date_th": "11-01-2569",
      "depart_date_en": "11-01-2026"
    },
    {
      "row_num": "79",
      "stop_no": 91,
      "station_code": 4196,
      "station_name": "Khao Suan Thurian",
      "is_begin": 0,
      "is_end": 0,
      "arrive_time": "17:39",
      "arriveplusdate": 0,
      "arrive_date_th": "11-01-2569",
      "arrive_date_en": "11-01-2026",
      "depart_time": "17:40",
      "departplusdate": 0,
      "depart_date_th": "11-01-2569",
      "depart_date_en": "11-01-2026"
    },
    {
      "row_num": "80",
      "stop_no": 92,
      "station_code": 4197,
      "station_name": "Khao Pip",
      "is_begin": 0,
      "is_end": 0,
      "arrive_time": "17:44",
      "arriveplusdate": 0,
      "arrive_date_th": "11-01-2569",
      "arrive_date_en": "11-01-2026",
      "depart_time": "17:45",
      "departplusdate": 0,
      "depart_date_th": "11-01-2569",
      "depart_date_en": "11-01-2026"
    },
    {
      "row_num": "81",
      "stop_no": 93,
      "station_code": 4199,
      "station_name": "Pak Tako",
      "is_begin": 0,
      "is_end": 0,
      "arrive_time": "17:50",
      "arriveplusdate": 0,
      "arrive_date_th": "11-01-2569",
      "arrive_date_en": "11-01-2026",
      "depart_time": "17:51",
      "departplusdate": 0,
      "depart_date_th": "11-01-2569",
      "depart_date_en": "11-01-2026"
    },
    {
      "row_num": "82",
      "stop_no": 94,
      "station_code": 4200,
      "station_name": "Tha Thong",
      "is_begin": 0,
      "is_end": 0,
      "arrive_time": "17:57",
      "arriveplusdate": 0,
      "arrive_date_th": "11-01-2569",
      "arrive_date_en": "11-01-2026",
      "depart_time": "17:58",
      "departplusdate": 0,
      "depart_date_th": "11-01-2569",
      "depart_date_en": "11-01-2026"
    },
    {
      "row_num": "83",
      "stop_no": 95,
      "station_code": 4201,
      "station_name": "Khuan Hin Mui",
      "is_begin": 0,
      "is_end": 0,
      "arrive_time": "18:02",
      "arriveplusdate": 0,
      "arrive_date_th": "11-01-2569",
      "arrive_date_en": "11-01-2026",
      "depart_time": "18:03",
      "departplusdate": 0,
      "depart_date_th": "11-01-2569",
      "depart_date_en": "11-01-2026"
    },
    {
      "row_num": "84",
      "stop_no": 96,
      "station_code": 4203,
      "station_name": "Lang Suan",
      "is_begin": 0,
      "is_end": 1,
      "arrive_time": "18:10",
      "arriveplusdate": 0,
      "arrive_date_th": "11-01-2569",
      "arrive_date_en": "11-01-2026",
      "depart_time": null,
      "departplusdate": null,
      "depart_date_th": null,
      "depart_date_en": "11-01-2026"
    }
  ]
}