{
  "masterId": 56,
  "operatingDays": [
    "Monday",
    "Tuesday",
    "Wednesday",
    "Thursday",
    "Friday",
    "Saturday",
    "Sunday"
  ],
  "offDays": [],
  "schedules": {},
  "trainData": {
    "train_code": "258",
    "begin": "Nam Tok",
    "end": "Thon Buri",
    "train_type": "Ordinary",
    "code": null,
    "line": "สายใต้",
    "bg_color": "#ffd966",
    "text_color": "#000000",
    "displayDate": null,
    "valid_from_th": "19-01-2568",
    "valid_until_th": null,
    "valid_from_en": "19-01-2025",
    "valid_until_en": null
  },
  "scheduleData": [
    {
      "row_num": "1",
      "stop_no": 1,
      "station_code": 4077,
      "station_name": "Nam Tok",
      "is_begin": 1,
      "is_end": 0,
      "arrive_time": null,
      "arriveplusdate": null,
      "arrive_date_th": null,
      "arrive_date_en": null,
      "depart_time": "13:00",
      "departplusdate": 0,
      "depart_date_th": "11-01-2569",
      "depart_date_en": null
    },
    {
      "row_num": "2",
      "stop_no": 5,
      "station_code": 4074,
      "station_name": "Ko Maha Mongkol",
      "is_begin": 0,
      "is_end": 0,
      "arrive_time": "13:14",
      "arriveplusdate": 0,
      "arrive_date_th": "11-01-2569",
      "arrive_date_en": "11-01-2026",
      "depart_time": "13:15",
      "departplusdate": 0,
      "depart_date_th": "11-01-2569",
      "depart_date_en": "11-01-2026"
    },
    {
      "row_num": "3",
      "stop_no": 6,
      "station_code": 4073,
      "station_name": "Wang Pho",
      "is_begin": 0,
      "is_end": 0,
      "arrive_time": "13:21",
      "arriveplusdate": 0,
      "arrive_date_th": "11-01-2569",
      "arrive_date_en": "11-01-2026",
      "depart_time": "13:22",
      "departplusdate": 0,
      "depart_date_th": "11-01-2569",
      "depart_date_en": "11-01-2026"
    },
    {
      "row_num": "4",
      "stop_no": 7,
      "station_code": 4072,
      "station_name": "Saphan Tam Krasae",
      "is_begin": 0,
      "is_end": 0,
      "arrive_time": "13:28",
      "arriveplusdate": 0,
      "arrive_date_th": "11-01-2569",
      "arrive_date_en": "11-01-2026",
      "depart_time": "13:29",
      "departplusdate": 0,
      "depart_date_th": "11-01-2569",
      "depart_date_en": "11-01-2026"
    },
    {
      "row_num": "5",
      "stop_no": 8,
      "station_code": 4071,
      "station_name": "Lumsum",
      "is_begin": 0,
      "is_end": 0,
      "arrive_time": "13:32",
      "arriveplusdate": 0,
      "arrive_date_th": "11-01-2569",
      "arrive_date_en": "11-01-2026",
      "depart_time": "13:33",
      "departplusdate": 0,
      "depart_date_th": "11-01-2569",
      "depart_date_en": "11-01-2026"
    },
    {
      "row_num": "6",
      "stop_no": 10,
      "station_code": 4069,
      "station_name": "Tha Kilen",
      "is_begin": 0,
      "is_end": 0,
      "arrive_time": "13:44",
      "arriveplusdate": 0,
      "arrive_date_th": "11-01-2569",
      "arrive_date_en": "11-01-2026",
      "depart_time": "13:45",
      "departplusdate": 0,
      "depart_date_th": "11-01-2569",
      "depart_date_en": "11-01-2026"
    },
    {
      "row_num": "7",
      "stop_no": 12,
      "station_code": 4066,
      "station_name": "Ban Kao",
      "is_begin": 0,
      "is_end": 0,
      "arrive_time": "13:57",
      "arriveplusdate": 0,
      "arrive_date_th": "11-01-2569",
      "arrive_date_en": "11-01-2026",
      "depart_time": "13:58",
      "departplusdate": 0,
      "depart_date_th": "11-01-2569",
      "depart_date_en": "11-01-2026"
    },
    {
      "row_num": "8",
      "stop_no": 14,
      "station_code": 4064,
      "station_name": "Wang Takhian",
      "is_begin": 0,
      "is_end": 0,
      "arrive_time": "14:06",
      "arriveplusdate": 0,
      "arrive_date_th": "11-01-2569",
      "arrive_date_en": "11-01-2026",
      "depart_time": "14:07",
      "departplusdate": 0,
      "depart_date_th": "11-01-2569",
      "depart_date_en": "11-01-2026"
    },
    {
      "row_num": "9",
      "stop_no": 15,
      "station_code": 4063,
      "station_name": "Wang Yen",
      "is_begin": 0,
      "is_end": 0,
      "arrive_time": "14:13",
      "arriveplusdate": 0,
      "arrive_date_th": "11-01-2569",
      "arrive_date_en": "11-01-2026",
      "depart_time": "14:14",
      "departplusdate": 0,
      "depart_date_th": "11-01-2569",
      "depart_date_en": "11-01-2026"
    },
    {
      "row_num": "10",
      "stop_no": 19,
      "station_code": 4058,
      "station_name": "Saphan Kwae Yai",
      "is_begin": 0,
      "is_end": 0,
      "arrive_time": "14:34",
      "arriveplusdate": 0,
      "arrive_date_th": "11-01-2569",
      "arrive_date_en": "11-01-2026",
      "depart_time": "14:35",
      "departplusdate": 0,
      "depart_date_th": "11-01-2569",
      "depart_date_en": "11-01-2026"
    },
    {
      "row_num": "11",
      "stop_no": 20,
      "station_code": 4057,
      "station_name": "Kanchanaburi",
      "is_begin": 0,
      "is_end": 0,
      "arrive_time": "14:40",
      "arriveplusdate": 0,
      "arrive_date_th": "11-01-2569",
      "arrive_date_en": "11-01-2026",
      "depart_time": "14:43",
      "departplusdate": 0,
      "depart_date_th": "11-01-2569",
      "depart_date_en": "11-01-2026"
    },
    {
      "row_num": "12",
      "stop_no": 22,
      "station_code": 4052,
      "station_name": "Thung Thong",
      "is_begin": 0,
      "is_end": 0,
      "arrive_time": "14:58",
      "arriveplusdate": 0,
      "arrive_date_th": "11-01-2569",
      "arrive_date_en": "11-01-2026",
      "depart_time": "14:59",
      "departplusdate": 0,
      "depart_date_th": "11-01-2569",
      "depart_date_en": "11-01-2026"
    },
    {
      "row_num": "13",
      "stop_no": 25,
      "station_code": 4048,
      "station_name": "Tha Rua Noi",
      "is_begin": 0,
      "is_end": 0,
      "arrive_time": "15:12",
      "arriveplusdate": 0,
      "arrive_date_th": "11-01-2569",
      "arrive_date_en": "11-01-2026",
      "depart_time": "15:13",
      "departplusdate": 0,
      "depart_date_th": "11-01-2569",
      "depart_date_en": "11-01-2026"
    },
    {
      "row_num": "14",
      "stop_no": 26,
      "station_code": 4045,
      "station_name": "Luk Kae",
      "is_begin": 0,
      "is_end": 0,
      "arrive_time": "15:25",
      "arriveplusdate": 0,
      "arrive_date_th": "11-01-2569",
      "arrive_date_en": "11-01-2026",
      "depart_time": "15:26",
      "departplusdate": 0,
      "depart_date_th": "11-01-2569",
      "depart_date_en": "11-01-2026"
    },
    {
      "row_num": "15",
      "stop_no": 27,
      "station_code": 4044,
      "station_name": "Sa Kosi Narai",
      "is_begin": 0,
      "is_end": 0,
      "arrive_time": "15:31",
      "arriveplusdate": 0,
      "arrive_date_th": "11-01-2569",
      "arrive_date_en": "11-01-2026",
      "depart_time": "15:35",
      "departplusdate": 0,
      "depart_date_th": "11-01-2569",
      "depart_date_en": "11-01-2026"
    },
    {
      "row_num": "16",
      "stop_no": 28,
      "station_code": 4043,
      "station_name": "Tanon Songpol",
      "is_begin": 0,
      "is_end": 0,
      "arrive_time": "15:43",
      "arriveplusdate": 0,
      "arrive_date_th": "11-01-2569",
      "arrive_date_en": "11-01-2026",
      "depart_time": "15:44",
      "departplusdate": 0,
      "depart_date_th": "11-01-2569",
      "depart_date_en": "11-01-2026"
    },
    {
      "row_num": "17",
      "stop_no": 29,
      "station_code": 4020,
      "station_name": "Nong Pla Duk Junction",
      "is_begin": 0,
      "is_end": 0,
      "arrive_time": "15:50",
      "arriveplusdate": 0,
      "arrive_date_th": "11-01-2569",
      "arrive_date_en": "11-01-2026",
      "depart_time": "15:51",
      "departplusdate": 0,
      "depart_date_th": "11-01-2569",
      "depart_date_en": "11-01-2026"
    },
    {
      "row_num": "18",
      "stop_no": 30,
      "station_code": 4019,
      "station_name": "Khlong Bang Tan",
      "is_begin": 0,
      "is_end": 0,
      "arrive_time": "15:58",
      "arriveplusdate": 0,
      "arrive_date_th": "11-01-2569",
      "arrive_date_en": "11-01-2026",
      "depart_time": "15:59",
      "departplusdate": 0,
      "depart_date_th": "11-01-2569",
      "depart_date_en": "11-01-2026"
    },
    {
      "row_num": "19",
      "stop_no": 31,
      "station_code": 4018,
      "station_name": "Phrong Madua",
      "is_begin": 0,
      "is_end": 0,
      "arrive_time": "16:05",
      "arriveplusdate": 0,
      "arrive_date_th": "11-01-2569",
      "arrive_date_en": "11-01-2026",
      "depart_time": "16:13",
      "departplusdate": 0,
      "depart_date_th": "11-01-2569",
      "depart_date_en": "11-01-2026"
    },
    {
      "row_num": "20",
      "stop_no": 32,
      "station_code": 4017,
      "station_name": "Sanam Chandra Palace",
      "is_begin": 0,
      "is_end": 0,
      "arrive_time": "16:19",
      "arriveplusdate": 0,
      "arrive_date_th": "11-01-2569",
      "arrive_date_en": "11-01-2026",
      "depart_time": "16:20",
      "departplusdate": 0,
      "depart_date_th": "11-01-2569",
      "depart_date_en": "11-01-2026"
    },
    {
      "row_num": "21",
      "stop_no": 33,
      "station_code": 4016,
      "station_name": "Nakhon Pathom",
      "is_begin": 0,
      "is_end": 0,
      "arrive_time": "16:23",
      "arriveplusdate": 0,
      "arrive_date_th": "11-01-2569",
      "arrive_date_en": "11-01-2026",
      "depart_time": "16:24",
      "departplusdate": 0,
      "depart_date_th": "11-01-2569",
      "depart_date_en": "11-01-2026"
    },
    {
      "row_num": "22",
      "stop_no": 34,
      "station_code": 4015,
      "station_name": "Ton Samrong",
      "is_begin": 0,
      "is_end": 0,
      "arrive_time": "16:28",
      "arriveplusdate": 0,
      "arrive_date_th": "11-01-2569",
      "arrive_date_en": "11-01-2026",
      "depart_time": "16:29",
      "departplusdate": 0,
      "depart_date_th": "11-01-2569",
      "depart_date_en": "11-01-2026"
    },
    {
      "row_num": "23",
      "stop_no": 35,
      "station_code": 4014,
      "station_name": "Tha Chalaep",
      "is_begin": 0,
      "is_end": 0,
      "arrive_time": "16:34",
      "arriveplusdate": 0,
      "arrive_date_th": "11-01-2569",
      "arrive_date_en": "11-01-2026",
      "depart_time": "16:35",
      "departplusdate": 0,
      "depart_date_th": "11-01-2569",
      "depart_date_en": "11-01-2026"
    },
    {
      "row_num": "24",
      "stop_no": 36,
      "station_code": 4013,
      "station_name": "Nakhon Chaisi",
      "is_begin": 0,
      "is_end": 0,
      "arrive_time": "16:40",
      "arriveplusdate": 0,
      "arrive_date_th": "11-01-2569",
      "arrive_date_en": "11-01-2026",
      "depart_time": "16:41",
      "departplusdate": 0,
      "depart_date_th": "11-01-2569",
      "depart_date_en": "11-01-2026"
    },
    {
      "row_num": "25",
      "stop_no": 37,
      "station_code": 4012,
      "station_name": "Wat Ngiu Rai",
      "is_begin": 0,
      "is_end": 0,
      "arrive_time": "16:46",
      "arriveplusdate": 0,
      "arrive_date_th": "11-01-2569",
      "arrive_date_en": "11-01-2026",
      "depart_time": "16:47",
      "departplusdate": 0,
      "depart_date_th": "11-01-2569",
      "depart_date_en": "11-01-2026"
    },
    {
      "row_num": "26",
      "stop_no": 38,
      "station_code": 4011,
      "station_name": "Khlong Maha Sawat",
      "is_begin": 0,
      "is_end": 0,
      "arrive_time": "16:51",
      "arriveplusdate": 0,
      "arrive_date_th": "11-01-2569",
      "arrive_date_en": "11-01-2026",
      "depart_time": "16:52",
      "departplusdate": 0,
      "depart_date_th": "11-01-2569",
      "depart_date_en": "11-01-2026"
    },
    {
      "row_num": "27",
      "stop_no": 39,
      "station_code": 4010,
      "station_name": "Wat Suwan",
      "is_begin": 0,
      "is_end": 0,
      "arrive_time": "16:56",
      "arriveplusdate": 0,
      "arrive_date_th": "11-01-2569",
      "arrive_date_en": "11-01-2026",
      "depart_time": "16:57",
      "departplusdate": 0,
      "depart_date_th": "11-01-2569",
      "depart_date_en": "11-01-2026"
    },
    {
      "row_num": "28",
      "stop_no": 40,
      "station_code": 4009,
      "station_name": "Sala Ya",
      "is_begin": 0,
      "is_end": 0,
      "arrive_time": "17:01",
      "arriveplusdate": 0,
      "arrive_date_th": "11-01-2569",
      "arrive_date_en": "11-01-2026",
      "depart_time": "17:02",
      "departplusdate": 0,
      "depart_date_th": "11-01-2569",
      "depart_date_en": "11-01-2026"
    },
    {
      "row_num": "29",
      "stop_no": 41,
      "station_code": 4008,
      "station_name": "Sala Thammasop",
      "is_begin": 0,
      "is_end": 0,
      "arrive_time": "17:08",
      "arriveplusdate": 0,
      "arrive_date_th": "11-01-2569",
      "arrive_date_en": "11-01-2026",
      "depart_time": "17:09",
      "departplusdate": 0,
      "depart_date_th": "11-01-2569",
      "depart_date_en": "11-01-2026"
    },
    {
      "row_num": "30",
      "stop_no": 43,
      "station_code": 4007,
      "station_name": "Banchimphli",
      "is_begin": 0,
      "is_end": 0,
      "arrive_time": "17:15",
      "arriveplusdate": 0,
      "arrive_date_th": "11-01-2569",
      "arrive_date_en": "11-01-2026",
      "depart_time": "17:16",
      "departplusdate": 0,
      "depart_date_th": "11-01-2569",
      "depart_date_en": "11-01-2026"
    },
    {
      "row_num": "31",
      "stop_no": 44,
      "station_code": 4004,
      "station_name": "Taling Chan Junction",
      "is_begin": 0,
      "is_end": 0,
      "arrive_time": "17:20",
      "arriveplusdate": 0,
      "arrive_date_th": "11-01-2569",
      "arrive_date_en": "11-01-2026",
      "depart_time": "17:26",
      "departplusdate": 0,
      "depart_date_th": "11-01-2569",
      "depart_date_en": "11-01-2026"
    },
    {
      "row_num": "32",
      "stop_no": 45,
      "station_code": 4003,
      "station_name": "Bang Ramat",
      "is_begin": 0,
      "is_end": 0,
      "arrive_time": "17:30",
      "arriveplusdate": 0,
      "arrive_date_th": "11-01-2569",
      "arrive_date_en": "11-01-2026",
      "depart_time": "17:31",
      "departplusdate": 0,
      "depart_date_th": "11-01-2569",
      "depart_date_en": "11-01-2026"
    },
    {
      "row_num": "33",
      "stop_no": 46,
      "station_code": 4434,
      "station_name": "Jaran Sanitwong",
      "is_begin": 0,
      "is_end": 0,
      "arrive_time": "17:36",
      "arriveplusdate": 0,
      "arrive_date_th": "11-01-2569",
      "arrive_date_en": "11-01-2026",
      "depart_time": "17:37",
      "departplusdate": 0,
      "depart_date_th": "11-01-2569",
      "depart_date_en": "11-01-2026"
    },
    {
      "row_num": "34",
      "stop_no": 47,
      "station_code": 4002,
      "station_name": "Thon Buri",
      "is_begin": 0,
      "is_end": 1,
      "arrive_time": "17:40",
      "arriveplusdate": 0,
      "arrive_date_th": "11-01-2569",
      "arrive_date_en": "11-01-2026",
      "depart_time": null,
      "departplusdate": null,
      "depart_date_th": null,
      "depart_date_en": "11-01-2026"
    }
  ]
}