[
  {
    "train_code": "260",
    "departure_from_start": "05:20",
    "arrival_at_current": "07:33",
    "departure_from_current": "07:34",
    "arrival_at_to_station": "07:50",
    "arrival_at_end": "09:35",
    "weekly_offday": "None",
    "operating_days": "Daily",
    "train_type": "Ordinary",
    "begin_station_name": "Tha Rua Noi",
    "end_station_name": "Sa Kosi Narai",
    "begin_station_code": 4048,
    "end_station_code": 4044
  },
  {
    "train_code": "258",
    "departure_from_start": "13:00",
    "arrival_at_current": "15:12",
    "departure_from_current": "15:13",
    "arrival_at_to_station": "15:31",
    "arrival_at_end": "17:40",
    "weekly_offday": "None",
    "operating_days": "Daily",
    "train_type": "Ordinary",
    "begin_station_name": "Tha Rua Noi",
    "end_station_name": "Sa Kosi Narai",
    "begin_station_code": 4048,
    "end_station_code": 4044
  }
]