[
  {
    "train_code": "4302",
    "departure_from_start": "04:30",
    "arrival_at_current": "05:18",
    "departure_from_current": "05:19",
    "arrival_at_to_station": "05:20",
    "arrival_at_end": "05:24",
    "weekly_offday": "None",
    "operating_days": "Daily",
    "train_type": "Commuter",
    "begin_station_name": "Wutthakat",
    "end_station_name": "Talat Phlu",
    "begin_station_code": 5002,
    "end_station_code": 5003
  },
  {
    "train_code": "4310",
    "departure_from_start": "05:20",
    "arrival_at_current": "06:11",
    "departure_from_current": "06:12",
    "arrival_at_to_station": "06:13",
    "arrival_at_end": "06:17",
    "weekly_offday": "None",
    "operating_days": "Daily",
    "train_type": "Commuter",
    "begin_station_name": "Wutthakat",
    "end_station_name": "Talat Phlu",
    "begin_station_code": 5002,
    "end_station_code": 5003
  },
  {
    "train_code": "4320",
    "departure_from_start": "05:55",
    "arrival_at_current": "06:48",
    "departure_from_current": "06:49",
    "arrival_at_to_station": "06:50",
    "arrival_at_end": "06:54",
    "weekly_offday": "None",
    "operating_days": "Daily",
    "train_type": "Commuter",
    "begin_station_name": "Wutthakat",
    "end_station_name": "Talat Phlu",
    "begin_station_code": 5002,
    "end_station_code": 5003
  },
  {
    "train_code": "4340",
    "departure_from_start": "06:25",
    "arrival_at_current": "07:23",
    "departure_from_current": "07:24",
    "arrival_at_to_station": "07:25",
    "arrival_at_end": "07:29",
    "weekly_offday": "None",
    "operating_days": "Daily",
    "train_type": "Commuter",
    "begin_station_name": "Wutthakat",
    "end_station_name": "Talat Phlu",
    "begin_station_code": 5002,
    "end_station_code": 5003
  },
  {
    "train_code": "4304",
    "departure_from_start": "07:00",
    "arrival_at_current": "07:51",
    "departure_from_current": "07:52",
    "arrival_at_to_station": "07:53",
    "arrival_at_end": "07:58",
    "weekly_offday": "None",
    "operating_days": "Daily",
    "train_type": "Commuter",
    "begin_station_name": "Wutthakat",
    "end_station_name": "Talat Phlu",
    "begin_station_code": 5002,
    "end_station_code": 5003
  },
  {
    "train_code": "4312",
    "departure_from_start": "08:00",
    "arrival_at_current": "08:57",
    "departure_from_current": "08:58",
    "arrival_at_to_station": "08:59",
    "arrival_at_end": "09:03",
    "weekly_offday": "None",
    "operating_days": "Daily",
    "train_type": "Commuter",
    "begin_station_name": "Wutthakat",
    "end_station_name": "Talat Phlu",
    "begin_station_code": 5002,
    "end_station_code": 5003
  },
  {
    "train_code": "4322",
    "departure_from_start": "09:35",
    "arrival_at_current": "10:26",
    "departure_from_current": "10:27",
    "arrival_at_to_station": "10:28",
    "arrival_at_end": "10:32",
    "weekly_offday": "None",
    "operating_days": "Daily",
    "train_type": "Commuter",
    "begin_station_name": "Wutthakat",
    "end_station_name": "Talat Phlu",
    "begin_station_code": 5002,
    "end_station_code": 5003
  },
  {
    "train_code": "4342",
    "departure_from_start": "10:40",
    "arrival_at_current": "11:33",
    "departure_from_current": "11:34",
    "arrival_at_to_station": "11:34",
    "arrival_at_end": "11:39",
    "weekly_offday": "None",
    "operating_days": "Daily",
    "train_type": "Commuter",
    "begin_station_name": "Wutthakat",
    "end_station_name": "Talat Phlu",
    "begin_station_code": 5002,
    "end_station_code": 5003
  },
  {
    "train_code": "4314",
    "departure_from_start": "11:45",
    "arrival_at_current": "12:38",
    "departure_from_current": "12:39",
    "arrival_at_to_station": "12:40",
    "arrival_at_end": "12:44",
    "weekly_offday": "None",
    "operating_days": "Daily",
    "train_type": "Commuter",
    "begin_station_name": "Wutthakat",
    "end_station_name": "Talat Phlu",
    "begin_station_code": 5002,
    "end_station_code": 5003
  },
  {
    "train_code": "4324",
    "departure_from_start": "13:15",
    "arrival_at_current": "14:08",
    "departure_from_current": "14:09",
    "arrival_at_to_station": "14:10",
    "arrival_at_end": "14:14",
    "weekly_offday": "None",
    "operating_days": "Daily",
    "train_type": "Commuter",
    "begin_station_name": "Wutthakat",
    "end_station_name": "Talat Phlu",
    "begin_station_code": 5002,
    "end_station_code": 5003
  },
  {
    "train_code": "4316",
    "departure_from_start": "14:25",
    "arrival_at_current": "15:13",
    "departure_from_current": "15:14",
    "arrival_at_to_station": "15:15",
    "arrival_at_end": "15:19",
    "weekly_offday": "None",
    "operating_days": "Daily",
    "train_type": "Commuter",
    "begin_station_name": "Wutthakat",
    "end_station_name": "Talat Phlu",
    "begin_station_code": 5002,
    "end_station_code": 5003
  },
  {
    "train_code": "4306",
    "departure_from_start": "15:25",
    "arrival_at_current": "16:14",
    "departure_from_current": "16:15",
    "arrival_at_to_station": "16:16",
    "arrival_at_end": "16:20",
    "weekly_offday": "None",
    "operating_days": "Daily",
    "train_type": "Commuter",
    "begin_station_name": "Wutthakat",
    "end_station_name": "Talat Phlu",
    "begin_station_code": 5002,
    "end_station_code": 5003
  },
  {
    "train_code": "4326",
    "departure_from_start": "16:00",
    "arrival_at_current": "16:50",
    "departure_from_current": "16:51",
    "arrival_at_to_station": "16:52",
    "arrival_at_end": "16:56",
    "weekly_offday": "None",
    "operating_days": "Daily",
    "train_type": "Commuter",
    "begin_station_name": "Wutthakat",
    "end_station_name": "Talat Phlu",
    "begin_station_code": 5002,
    "end_station_code": 5003
  },
  {
    "train_code": "4344",
    "departure_from_start": "16:30",
    "arrival_at_current": "17:23",
    "departure_from_current": "17:24",
    "arrival_at_to_station": "17:25",
    "arrival_at_end": "17:29",
    "weekly_offday": "None",
    "operating_days": "Daily",
    "train_type": "Commuter",
    "begin_station_name": "Wutthakat",
    "end_station_name": "Talat Phlu",
    "begin_station_code": 5002,
    "end_station_code": 5003
  },
  {
    "train_code": "4308",
    "departure_from_start": "17:35",
    "arrival_at_current": "18:20",
    "departure_from_current": "18:21",
    "arrival_at_to_station": "18:22",
    "arrival_at_end": "18:26",
    "weekly_offday": "None",
    "operating_days": "Daily",
    "train_type": "Commuter",
    "begin_station_name": "Wutthakat",
    "end_station_name": "Talat Phlu",
    "begin_station_code": 5002,
    "end_station_code": 5003
  },
  {
    "train_code": "4328",
    "departure_from_start": "18:10",
    "arrival_at_current": "18:56",
    "departure_from_current": "18:57",
    "arrival_at_to_station": "18:58",
    "arrival_at_end": "19:02",
    "weekly_offday": "None",
    "operating_days": "Daily",
    "train_type": "Commuter",
    "begin_station_name": "Wutthakat",
    "end_station_name": "Talat Phlu",
    "begin_station_code": 5002,
    "end_station_code": 5003
  },
  {
    "train_code": "4346",
    "departure_from_start": "19:00",
    "arrival_at_current": "19:54",
    "departure_from_current": "19:55",
    "arrival_at_to_station": "19:56",
    "arrival_at_end": "20:00",
    "weekly_offday": "None",
    "operating_days": "Daily",
    "train_type": "Commuter",
    "begin_station_name": "Wutthakat",
    "end_station_name": "Talat Phlu",
    "begin_station_code": 5002,
    "end_station_code": 5003
  }
]